sbcdp/__init__.py
sbcdp/__version__.py
sbcdp/chrome.py
sbcdp/settings.py
sbcdp/api/__init__.py
sbcdp/api/action.py
sbcdp/api/base.py
sbcdp/api/dom.py
sbcdp/api/gui.py
sbcdp/api/navigation.py
sbcdp/api/network.py
sbcdp/api/page_info.py
sbcdp/api/wait.py
sbcdp/core/__init__.py
sbcdp/core/colored_traceback.py
sbcdp/core/detect_b_ver.py
sbcdp/core/download_helper.py
sbcdp/core/encoded_images.py
sbcdp/core/proxy_helper.py
sbcdp/driver/__init__.py
sbcdp/driver/_contradict.py
sbcdp/driver/browser.py
sbcdp/driver/cdp_util.py
sbcdp/driver/config.py
sbcdp/driver/connection.py
sbcdp/driver/element.py
sbcdp/driver/tab.py
sbcdp/fixtures/__init__.py
sbcdp/fixtures/constants.py
sbcdp/fixtures/css_to_xpath.py
sbcdp/fixtures/errors.py
sbcdp/fixtures/js_utils.py
sbcdp/fixtures/page_actions.py
sbcdp/fixtures/page_utils.py
sbcdp/fixtures/shared_utils.py
sbcdp/fixtures/xpath_to_css.py
sbcdp-1.3.2.dist-info/LICENSE
sbcdp-1.3.2.dist-info/METADATA
sbcdp-1.3.2.dist-info/WHEEL
sbcdp-1.3.2.dist-info/top_level.txt
sbcdp-1.3.2.dist-info/RECORD
