Metadata-Version: 2.1
Name: sbcdp
Version: 1.3.2
Summary: SBCDP - Pure CDP (Chrome DevTools Protocol) Automation Framework
Home-page: https://github.com/ConlinH/sbcdp
Author: conlin
Author-email: 995018884@qq.com
License: MIT
Project-URL: Homepage, https://github.com/ConlinH/sbcdp
Project-URL: Source, https://github.com/ConlinH/sbcdp
Project-URL: Repository, https://github.com/ConlinH/sbcdp
Project-URL: Bug Tracker, https://github.com/ConlinH/sbcdp/issues
Project-URL: Documentation, https://github.com/ConlinH/sbcdp#readme
Keywords: automation,cdp,chrome,devtools,browser,scraping,testing,async,sync
Classifier: Development Status :: 5 - Production/Stable
Classifier: Environment :: Console
Classifier: Framework :: Pytest
Classifier: Intended Audience :: Developers
Classifier: Intended Audience :: Information Technology
Classifier: License :: OSI Approved :: MIT License
Classifier: Operating System :: MacOS :: MacOS X
Classifier: Operating System :: Microsoft :: Windows
Classifier: Operating System :: POSIX :: Linux
Classifier: Programming Language :: Python
Classifier: Programming Language :: Python :: 3
Classifier: Programming Language :: Python :: 3.8
Classifier: Programming Language :: Python :: 3.9
Classifier: Programming Language :: Python :: 3.10
Classifier: Programming Language :: Python :: 3.11
Classifier: Programming Language :: Python :: 3.12
Classifier: Programming Language :: Python :: 3.13
Classifier: Topic :: Internet
Classifier: Topic :: Internet :: WWW/HTTP :: Browsers
Classifier: Topic :: Scientific/Engineering
Classifier: Topic :: Software Development
Classifier: Topic :: Software Development :: Quality Assurance
Classifier: Topic :: Software Development :: Testing
Classifier: Topic :: Software Development :: Testing :: Acceptance
Classifier: Topic :: Software Development :: Testing :: Traffic Generation
Classifier: Topic :: Utilities
Requires-Python: >=3.8
License-File: LICENSE
Requires-Dist: requests
Requires-Dist: loguru
Requires-Dist: mycdp >=1.0.0
Requires-Dist: cssselect >=1.3.0
Requires-Dist: fasteners >=0.19
Requires-Dist: colorama >=0.4.6
Requires-Dist: websockets >=11.0.3
Provides-Extra: test
Requires-Dist: pytest >=7.0.0 ; extra == 'test'
Requires-Dist: pytest-asyncio >=0.21.0 ; extra == 'test'
Requires-Dist: pytest-cov >=4.0.0 ; extra == 'test'
